{
    "$schema": "/data/artifacts/.assets/schemas/ai_main_schema.json",
    "schema_version": "v10",
    "ai_project_name": "Project_name_128762",
    "display_name": "Smart Asset Tracking",
    "description": "Packages condition classification using MLC to detect stationary (upright or not), moving and shaking states.\n\nSimply hold the board as a box and start testing it.",
    "type": "industrial",
    "uuid": "b5968ad0-f3aa-451b-bc2a-05d0c79ac9c7",
    "version": "1.0.0",
    "creation_time": "2024-10-02 20:41:40.705776",
    "last_update_time": "2024-10-02 20:41:40.705776",
    "models": [
        {
            "uuid": "24f8686b-8c7d-4b94-98f2-b14d57b86d92",
            "name": "smart_asset_tracking",
            "description": "Model to recognize position and orientation of a tracked item, created with an Auto-ML based approach.",
            "creation_time": "2024-10-02 20:41:40.705790",
            "last_update_time": "2024-10-02 20:41:40.705794",
            "metadata": {
                "type": "classifier",
                "classes": [
                    "stationary_upright",
                    "stationary_not_upright",
                    "motion",
                    "shaken"
                ]
            },
            "dataset": {
                "dataset_id": "01j97ff4nqm5g3wfyhb96skapz",
                "name": "Asset Tracking"
            },
            "target": {
                "type": "mlc",
                "component": "lsm6dsv16x",
                "device": "steval-mkboxpro"
            },
            "data_sufficiency": {
                "creation_time": null,
                "last_update_time": null,
                "runtime": {
                    "type": "job",
                    "jobs": [
                        {
                            "name": "mlctools-ds-job",
                            "version": null,
                            "template_id": null
                        }
                    ]
                },
                "configuration": null,
                "artifacts": [
                    "activities_training.json",
                    "counts.json",
                    "feat_names.json",
                    "hnne.pkl",
                    "kmeans_cluster_labels.json",
                    "my_kmeans.json",
                    "my_tree.onnx",
                    "my_tree.txt",
                    "window_size_odr_channels.json"
                ],
                "reports": []
            },
            "training": {
                "creation_time": "2024-10-02 20:42:23.281390",
                "last_update_time": "2024-10-02 20:42:23.281395",
                "runtime": {
                    "type": "job",
                    "jobs": []
                },
                "configuration": "configuration.json",
                "artifacts": [
                    "lsm6dsv16x_mlc.ucf",
                    "lsm6dsv16x_mlc.h"
                ],
                "reports": [
                    "report.json"
                ]
            },
            "codegen": null,
            "building": null
        }
    ],
    "applications": [
        {
            "uuid": "6a0a6af6-3246-4a6e-b567-28c5851ee863",
            "type": "gateway",
            "device_template_uri": "/e2e_systems/gateway/dtmi/appconfig/gateway/MLC_GATEWAY-5.expanded.json",
            "device_template_id": "dtmi:appconfig:gateway:MLC_GATEWAY;5",
            "device_manifest_uri": "/e2e_systems/gateway/dtmi/appconfig/gateway/MLC_GATEWAY-5.manifest.arm64v8.json",
            "image_uri": "/e2e_systems/gateway/images/raspberrypi/edge_gateway_production_20241001_1_2_0_rc1.img.gz",
            "module_id": "edgeMLC"
        },
        {
            "uuid": "955488a5-b72a-4091-a12c-be6e7b1faaa8",
            "type": "datalogging",
            "device_template_uri": "/dtmi/appconfig/steval_mkboxpro/FP_SNS_DATALOG2_Datalog2-5.expanded.json",
            "device_template_id": "dtmi:appconfig:steval_mkboxpro:FP_SNS_DATALOG2_Datalog2;5",
            "binary_uri": "/bluestsdkv2/bin/steval-mkboxpro/FP-SNS-DATALOG2_Datalog2_2_2_0.bin",
            "binary_id": 281,
            "protocol": 2
        },
        {
            "uuid": "cab1c7ce-c26a-4036-adeb-d097615dfa0f",
            "type": "inference",
            "device_template_uri": "/dtmi/appconfig/steval_mkboxpro/AI_INERTIAL-1.expanded.json",
            "device_template_id": "dtmi:appconfig:steval_mkboxpro:AI_INERTIAL;1",
            "binary_uri": "/usb/bin/steval-mkboxpro/AI-INERTIAL_AssetTrackingOnMLC_1_1_0.bin",
            "binary_id": 336,
            "protocol": 1
        }
    ],
    "deployments": [
        {
            "uuid": "ddfdb86e-f0ac-46d1-a3ad-fef0d367a7bc",
            "display_name": "Smart Asset Tracking end-to-end system with SensorTile.box PRO.",
            "description": "End-to-end system deployment for Smart Asset Tracking scenario.",
            "last_update_time": null,
            "last_deploy_result": null,
            "cloud_params": {
                "type": "azure_iotc",
                "app_url": null
            },
            "gateway": [
                {
                    "device_id": "gateway_0",
                    "gateway_id": null,
                    "description": "Gateway device at position 0.",
                    "application": "6a0a6af6-3246-4a6e-b567-28c5851ee863",
                    "wifi_mode": "off"
                }
            ],
            "leaf": [
                {
                    "device_id": "leaf_0",
                    "gateway_id": "gateway_0",
                    "description": "Leaf device at position 0.",
                    "datalogging": {
                        "application": "955488a5-b72a-4091-a12c-be6e7b1faaa8",
                        "firmware_update": false
                    },
                    "inference": {
                        "application": "cab1c7ce-c26a-4036-adeb-d097615dfa0f",
                        "firmware_update": false,
                        "models": [
                            {
                                "model_name_reference": "smart_asset_tracking",
                                "artifact_type": "ucf",
                                "component_name": "lsm6dsv16x_mlc"
                            }
                        ]
                    }
                }
            ]
        }
    ]
}