{
    "uuid": "976ba822-542a-4d4e-82cc-3ff52740fa50",
    "ai_project_name": "proj_1778236459724",
    "type": null,
    "display_name": null,
    "description": null,
    "version": null,
    "schema_version": null,
    "last_update_time": "2026-05-08 10:34:21.046247",
    "creation_time": "2026-05-08 10:34:21.046247",
    "project_owner_uuid": "2b4e45b0-0835-420a-b81e-00c7c96e6a74",
    "models": [
        {
            "uuid": "abc89c42-b873-4abf-9a2c-258f3a9d8efa",
            "name": "model_example",
            "dataset": {
                "name": "01hy0rzc8jfhk5svwbb9reze42",
                "dataset_id": "01hy0rzc8jfhk5svwbb9reze42"
            },
            "metadata": {
                "type": "classifier",
                "classes": null
            },
            "target": {
                "type": "mlc",
                "component": "lsm6dsv16x",
                "device": "steval-mkboxpro"
            },
            "creation_time": "2026-05-08 10:34:23.506354",
            "last_update_time": "2026-05-08 10:34:23.506364",
            "model_owner_uuid": "2b4e45b0-0835-420a-b81e-00c7c96e6a74"
        }
    ],
    "deployments": [],
    "applications": []
}